pyoverlapped/__init__.py
pyoverlapped/bindings.py
pyoverlapped/overlapped.py
pyoverlapped/structures.py
pyoverlapped-1.0.1.dist-info/LICENSE
pyoverlapped-1.0.1.dist-info/METADATA
pyoverlapped-1.0.1.dist-info/WHEEL
pyoverlapped-1.0.1.dist-info/top_level.txt
pyoverlapped-1.0.1.dist-info/RECORD
