Metadata-Version: 2.1
Name: pyoverlapped
Version: 1.0.1
Summary: Lovely Spam! Wonderful Spam!
License:                     GNU GENERAL PUBLIC LICENSE
Keywords: egg,bacon,sausage,tomatoes,Lobster Thermidor
Classifier: Development Status :: 5 - Production/Stable
Classifier: Environment :: Console
Classifier: Intended Audience :: Developers
Classifier: License :: OSI Approved :: GNU General Public License v3 (GPLv3)
Classifier: Operating System :: Microsoft :: Windows
Classifier: Topic :: Software Development :: Libraries
Requires-Python: >=3.8
License-File: LICENSE
